xsmpy-0.3.6.dist-info/METADATA
xsmpy-0.3.6.dist-info/WHEEL
xsmpy/__init__.py
xsmpy/pool.py
xsmpy/xsmpy.cpython-311-darwin.so
xsmpy-0.3.6.dist-info/RECORD
